odoo/addons/l10n_br_currency_rate_update/README.rst
odoo/addons/l10n_br_currency_rate_update/__init__.py
odoo/addons/l10n_br_currency_rate_update/__manifest__.py
odoo/addons/l10n_br_currency_rate_update/i18n/l10n_br_currency_rate_update.pot
odoo/addons/l10n_br_currency_rate_update/i18n/pt_BR.po
odoo/addons/l10n_br_currency_rate_update/models/__init__.py
odoo/addons/l10n_br_currency_rate_update/models/res_currency_rate_provider_bcb.py
odoo/addons/l10n_br_currency_rate_update/readme/CONFIGURE.rst
odoo/addons/l10n_br_currency_rate_update/readme/CONTRIBUTORS.rst
odoo/addons/l10n_br_currency_rate_update/readme/DESCRIPTION.rst
odoo/addons/l10n_br_currency_rate_update/readme/USAGE.rst
odoo/addons/l10n_br_currency_rate_update/static/description/icon.png
odoo/addons/l10n_br_currency_rate_update/static/description/index.html
odoo/addons/l10n_br_currency_rate_update/tests/__init__.py
odoo/addons/l10n_br_currency_rate_update/tests/test_currency_rate_update_bcb.py
odoo13_addon_l10n_br_currency_rate_update-13.0.1.0.1.dev4.dist-info/METADATA
odoo13_addon_l10n_br_currency_rate_update-13.0.1.0.1.dev4.dist-info/WHEEL
odoo13_addon_l10n_br_currency_rate_update-13.0.1.0.1.dev4.dist-info/top_level.txt
odoo13_addon_l10n_br_currency_rate_update-13.0.1.0.1.dev4.dist-info/RECORD
